Aliceblue_Without_Api/__init__.py
Aliceblue_Without_Api/alice.py
aliceBlueWithoutApi/__init__.py
aliceBlueWithoutApi/alice.py
aliceblue_fetch_data/__init__.py
aliceblue_fetch_data/alice.py
alicelue_brocker_wihtoutapi/__init__.py
alicelue_brocker_wihtoutapi/alice.py
fyers_withoutapi/__init__.py
fyers_withoutapi/fyers.py
zerodha_without_api/__init__.py
zerodha_without_api/zerodha.py
aliceblue_fetch_data-0.0.1.dist-info/LICENSE
aliceblue_fetch_data-0.0.1.dist-info/METADATA
aliceblue_fetch_data-0.0.1.dist-info/WHEEL
aliceblue_fetch_data-0.0.1.dist-info/top_level.txt
aliceblue_fetch_data-0.0.1.dist-info/RECORD
